voice_easy/__init__.py
voice_easy/voice_easy.py
voice_easy-0.0.9.dist-info/LICENSE
voice_easy-0.0.9.dist-info/METADATA
voice_easy-0.0.9.dist-info/WHEEL
voice_easy-0.0.9.dist-info/top_level.txt
voice_easy-0.0.9.dist-info/RECORD
