Metadata-Version: 2.1
Name: voice-easy
Version: 0.0.9
Summary: voice easy
Home-page: https://github.com/Yoon-JinSeok/voice-easy
Author: yoonjinseok
Author-email: insomang@hanmail.net
Keywords: sounddevice,speech_recognition
Classifier: Programming Language :: Python :: 3.6
Classifier: Programming Language :: Python :: 3.7
Classifier: Programming Language :: Python :: 3.8
Classifier: Programming Language :: Python :: 3.9
Requires-Python: >=3.6
License-File: LICENSE
Requires-Dist: sounddevice
Requires-Dist: scipy
Requires-Dist: SpeechRecognition
Requires-Dist: pyaudio
